{
  "swagger": "2.0",
  "info": {
    "version": "1.0.0",
    "title": "Soul Shop API",
    "description": "API de compras"
  },
  "host": "localhost:3000",
  "basePath": "/",
  "tags": [
    {
      "name": "valePresente",
      "description": "EndPoint"
    },
    {
      "name": "Produtos",
      "description": "EndPoint para contas financeiras"
    }
  ],
  "schemes": [
    "http"
  ],
  "consumes": [
    "application/json",
    "application/xml"
  ],
  "produces": [
    "application/json"
  ],
  "paths": {
    "/": {
      "get": {
        "description": "",
        "parameters": [],
        "responses": {}
      }
    }
  }
}